neuroencoder/__init__.py
neuroencoder-0.0.4.dist-info/METADATA
neuroencoder-0.0.4.dist-info/WHEEL
neuroencoder-0.0.4.dist-info/top_level.txt
neuroencoder-0.0.4.dist-info/RECORD
