Metadata-Version: 2.1
Name: neuroencoder
Version: 0.0.4
Summary: A package for processing temporal neural data, including spike trains, LFP, and EEG
Home-page: https://github.com/avocardio/neuroencoder
Author: M.K.
Author-email: max@neuroencoder.com
License: UNKNOWN
Platform: UNKNOWN
Classifier: Development Status :: 2 - Pre-Alpha
Classifier: Intended Audience :: Healthcare Industry
Classifier: Intended Audience :: Science/Research
Classifier: License :: Other/Proprietary License
Classifier: Programming Language :: Python :: 3
Requires-Dist: numpy
Requires-Dist: pyedflib
Requires-Dist: tensorflow
Requires-Dist: tqdm
